fastfuzzy/__init__.py
fastfuzzy/fastfuzzy.py
fastfuzzy/settings.py
fastfuzzy-0.0.6.dist-info/LICENSE
fastfuzzy-0.0.6.dist-info/METADATA
fastfuzzy-0.0.6.dist-info/WHEEL
fastfuzzy-0.0.6.dist-info/top_level.txt
fastfuzzy-0.0.6.dist-info/RECORD
