Metadata-Version: 2.1
Name: fastfuzzy
Version: 0.0.6
Summary: Fast fuzzy string matching.
Home-page: https://gitlab.com/carschno/fastfuzzy
Author: Carsten Schnober
Author-email: carschno@gmail.com
License: MIT
Project-URL: Source, https://gitlab.com/carschno/fastfuzzy
Project-URL: PyPi, https://pypi.org/project/fastfuzzy/
Keywords: fuzzy string matching index q-gram
Platform: UNKNOWN
Classifier: Programming Language :: Python :: 3
Classifier: License :: OSI Approved :: MIT License
Classifier: Operating System :: OS Independent
Requires-Python: >=3.7,<3.9
Requires-Dist: abydos (==0.5.0)
Requires-Dist: tqdm (==4.55.1)
Provides-Extra: test
Requires-Dist: pytest (==6.2.1) ; extra == 'test'
Requires-Dist: pytest-cov (==2.10.1) ; extra == 'test'
